handelsregister_webdriver/__init__.py
handelsregister_webdriver/handelsregister_wd.py
handelsregister_webdriver-0.0.2.dist-info/METADATA
handelsregister_webdriver-0.0.2.dist-info/WHEEL
handelsregister_webdriver-0.0.2.dist-info/licenses/LICENSE
handelsregister_webdriver-0.0.2.dist-info/RECORD
